flightsql/__init__.py
flightsql/client.py
flightsql/dbapi.py
flightsql/exceptions.py
flightsql/flightsql_pb2.py
flightsql/sqlalchemy.py
flightsql/util.py
flightsql_dbapi-0.2.2.dist-info/METADATA
flightsql_dbapi-0.2.2.dist-info/WHEEL
flightsql_dbapi-0.2.2.dist-info/entry_points.txt
flightsql_dbapi-0.2.2.dist-info/licenses/LICENSE
flightsql_dbapi-0.2.2.dist-info/RECORD
