Metadata-Version: 2.1
Name: flightsql-dbapi
Version: 0.2.2
Summary: DB API 2 and SQLAlchemy adapter for Flight SQL
Project-URL: Homepage, https://github.com/influxdata/flightsql-dbapi
Author-email: Brett Buddin <brett@buddin.org>
License-File: LICENSE
Classifier: License :: OSI Approved :: Apache Software License
Classifier: Operating System :: OS Independent
Classifier: Programming Language :: Python :: 3
Requires-Python: >=3.8
Requires-Dist: protobuf>=4.21.0
Requires-Dist: pyarrow>=14.0.1
Requires-Dist: sqlalchemy<2.0
Provides-Extra: dev
Requires-Dist: build; extra == 'dev'
Requires-Dist: flightsql-dbapi[lint,test]; extra == 'dev'
Requires-Dist: pdoc; extra == 'dev'
Provides-Extra: lint
Requires-Dist: black; extra == 'lint'
Requires-Dist: flake8; extra == 'lint'
Requires-Dist: isort>5.10.0; extra == 'lint'
Requires-Dist: mypy>1.5.0; extra == 'lint'
Requires-Dist: pyproject-flake8; extra == 'lint'
Requires-Dist: toml-cli; extra == 'lint'
Requires-Dist: types-protobuf; extra == 'lint'
Provides-Extra: test
Requires-Dist: pandas>2.0; extra == 'test'
Requires-Dist: pytest; extra == 'test'
Requires-Dist: pytest-cov[all]; extra == 'test'
